adventure/README.txt
adventure/__init__.py
adventure/__main__.py
adventure/advent.dat
adventure/data.py
adventure/game.py
adventure/model.py
adventure/prompt.py
adventure/tests/__init__.py
adventure/tests/syntax.txt
adventure/tests/test_commands.py
adventure/tests/test_data.py
adventure/tests/test_walks.py
adventure/tests/vignettes.txt
adventure/tests/walkthrough1.txt
adventure/tests/walkthrough2.txt
adventure/tests/walkthrough3.txt
adventure/tests/walkthrough4.txt
adventure-1.7.dist-info/LICENSE.ASF-2
adventure-1.7.dist-info/METADATA
adventure-1.7.dist-info/WHEEL
adventure-1.7.dist-info/entry_points.txt
adventure-1.7.dist-info/top_level.txt
adventure-1.7.dist-info/RECORD
