Metadata-Version: 2.1
Name: adventure
Version: 1.7
Summary: Colossal Cave adventure game at the Python prompt
Home-page: https://github.com/brandon-rhodes/python-adventure
Author: Brandon Craig Rhodes
Author-email: brandon@rhodesmill.org
Classifier: Development Status :: 6 - Mature
Classifier: Environment :: Console
Classifier: Intended Audience :: End Users/Desktop
Classifier: License :: OSI Approved :: Apache Software License
Classifier: Programming Language :: Python :: 3
Classifier: Programming Language :: Python :: 3.2
Classifier: Topic :: Games/Entertainment
License-File: LICENSE.ASF-2
